ucimlrepo/__init__.py
ucimlrepo/dotdict.py
ucimlrepo/fetch.py
ucimlrepo/test.py
ucimlrepo-0.0.7.dist-info/LICENSE
ucimlrepo-0.0.7.dist-info/METADATA
ucimlrepo-0.0.7.dist-info/WHEEL
ucimlrepo-0.0.7.dist-info/top_level.txt
ucimlrepo-0.0.7.dist-info/RECORD
