Metadata-Version: 2.1
Name: ucimlrepo
Version: 0.0.7
Summary: Package to easily import datasets from the UC Irvine Machine Learning Repository into scripts and notebooks.
Home-page: https://github.com/uci-ml-repo/ucimlrepo
Author: Philip Truong
Author-email: Philip Truong <ucirepository@gmail.com>
Project-URL: Homepage, https://github.com/uci-ml-repo/ucimlrepo/tree/main
Project-URL: Bug Tracker, https://github.com/uci-ml-repo/ucimlrepo/issues
Classifier: Programming Language :: Python :: 3
Classifier: License :: OSI Approved :: MIT License
Classifier: Operating System :: OS Independent
Requires-Python: >=3.7
License-File: LICENSE
Requires-Dist: pandas>=1.0.0
Requires-Dist: certifi>=2020.12.5
